{
  "schemaVersion": "onslaught-rebuild-command-tape.v1",
  "name": "first-flight",
  "seed": 2836905711,
  "durationTicks": 150,
  "expectedFinalStateHash": "6af37ac096ac8842907b7658bc42de08e4e9146431df05b55518cb85e3a72eba",
  "expectedTraceHash": "5153dd6feadfe23aa9b309d87e6184b20cbdd93a687e5d0f4d8051bce56c3534",
  "spans": [
    {
      "startTick": 0,
      "durationTicks": 20,
      "moveX": 0,
      "moveZ": 1,
      "toggleMode": false,
      "fire": false,
      "reset": false
    },
    {
      "startTick": 20,
      "durationTicks": 25,
      "moveX": 0,
      "moveZ": 0,
      "toggleMode": false,
      "fire": true,
      "reset": false
    },
    {
      "startTick": 45,
      "durationTicks": 1,
      "moveX": 0,
      "moveZ": 0,
      "toggleMode": true,
      "fire": false,
      "reset": false
    },
    {
      "startTick": 60,
      "durationTicks": 30,
      "moveX": 1,
      "moveZ": 1,
      "toggleMode": false,
      "fire": false,
      "reset": false
    },
    {
      "startTick": 90,
      "durationTicks": 1,
      "moveX": 0,
      "moveZ": 0,
      "toggleMode": true,
      "fire": false,
      "reset": false
    },
    {
      "startTick": 105,
      "durationTicks": 30,
      "moveX": -1,
      "moveZ": 0,
      "toggleMode": false,
      "fire": false,
      "reset": false
    }
  ]
}
